stx_security_filter/__init__.py
stx_security_filter/checker.py
stx_security_filter-0.1.2.dist-info/licenses/LICENSE
stx_security_filter-0.1.2.dist-info/METADATA
stx_security_filter-0.1.2.dist-info/WHEEL
stx_security_filter-0.1.2.dist-info/top_level.txt
stx_security_filter-0.1.2.dist-info/RECORD
