Metadata-Version: 2.4
Name: stx-security-filter
Version: 0.1.2
Summary: Simple Python utility to detect malicious GET input
Author: Ajish Stephen
Author-email: info@ajishstephen.com
Requires-Python: >=3.6
License-File: LICENSE
Dynamic: author
Dynamic: author-email
Dynamic: description
Dynamic: description-content-type
Dynamic: license-file
Dynamic: requires-python
Dynamic: summary
